JDistributer/__init__.py
JDistributer/common_define.py
JDistributer/noreply_consumer.py
JDistributer/noreply_producer.py
JDistributer/reply_consumer.py
JDistributer/reply_group_consumer.py
JDistributer/reply_producer.py
JDistributer-0.0.2.dist-info/METADATA
JDistributer-0.0.2.dist-info/WHEEL
JDistributer-0.0.2.dist-info/top_level.txt
JDistributer-0.0.2.dist-info/RECORD
