Metadata-Version: 2.1
Name: JDistributer
Version: 0.0.2
Summary: JDistributer Demo
Home-page: https://github.com/ZhengqiaoWang/JDistributer
Author: ZhengqiaoWang
Author-email: me@zhengqiao.wang
License: MIT
Classifier: License :: OSI Approved :: MIT License
Classifier: Programming Language :: Python
Classifier: Programming Language :: Python :: 3
Classifier: Programming Language :: Python :: 3.6
Classifier: Programming Language :: Python :: Implementation :: CPython
Classifier: Programming Language :: Python :: Implementation :: PyPy
Requires-Python: >=3.6.0
Requires-Dist: redis
Requires-Dist: hiredis
